{
  "version": 1,
  "skills": {
    "accessibility": {
      "source": "addyosmani/web-quality-skills",
      "sourceType": "github",
      "skillPath": "skills/accessibility/SKILL.md",
      "computedHash": "10e83284d3395ab5ec2f2db602b663480a37a4ff404d16510eefe86b034fcc1a"
    },
    "design-taste-frontend": {
      "source": "Leonxlnx/taste-skill",
      "sourceType": "github",
      "skillPath": "skills/taste-skill/SKILL.md",
      "computedHash": "6d838b246d0e35d0b53f4f23f98ba7a1dd561937e64f7d0c7553b0928e376c3e"
    },
    "fastapi": {
      "source": "fastapi/fastapi",
      "sourceType": "github",
      "skillPath": "fastapi/.agents/skills/fastapi/SKILL.md",
      "computedHash": "ee23d5285caf055cf164ff45dd34888d381143564666baacab8aa786f22e413a"
    },
    "full-output-enforcement": {
      "source": "Leonxlnx/taste-skill",
      "sourceType": "github",
      "skillPath": "skills/output-skill/SKILL.md",
      "computedHash": "26bd29ce2c7666b2d503609bf466bd32290822e91f0e984147048dbb924"
    },
    "nextjs": {
      "source": "vercel-labs/vercel-plugin",
      "sourceType": "github",
      "skillPath": "skills/nextjs/SKILL.md",
      "computedHash": "e1175545611b2e63b6cbb88b355cd1788cdd2392525bc60faeab1744df1a0264"
    },
    "playwright-cli": {
      "source": "microsoft/playwright-cli",
      "sourceType": "github",
      "skillPath": "skills/playwright-cli/SKILL.md",
      "computedHash": "84495cfda62b6c012afc4cc34a0c35bfc7923ba35983b8c04ce4cace0f35a5d8"
    },
    "shadcn": {
      "source": "shadcn/ui",
      "sourceType": "github",
      "skillPath": "skills/shadcn/SKILL.md",
      "computedHash": "8f8bcc9024aa068245fac646d654a18c80280e4b06112ccd3e691a8c96cd66bd"
    }
  }
}
